ebcc/__init__.py
ebcc/backend/__init__.py
ebcc/backend/_ctf.py
ebcc/backend/_cupy.py
ebcc/backend/_jax.py
ebcc/backend/_numpy.py
ebcc/backend/_tensorflow.py
ebcc/cc/__init__.py
ebcc/cc/base.py
ebcc/cc/gebcc.py
ebcc/cc/rebcc.py
ebcc/cc/uebcc.py
ebcc/codegen/GCC2.py
ebcc/codegen/GCC3.py
ebcc/codegen/GCCD.py
ebcc/codegen/GCCSD.py
ebcc/codegen/GCCSDT.py
ebcc/codegen/GCCSDTQ.py
ebcc/codegen/GCCSD_SD_1_1.py
ebcc/codegen/GCCSD_SD_1_2.py
ebcc/codegen/GCCSD_S_1_1.py
ebcc/codegen/GCCSDwtwp.py
ebcc/codegen/GCCSDxTx.py
ebcc/codegen/GMP2.py
ebcc/codegen/GMP3.py
ebcc/codegen/GQCISD.py
ebcc/codegen/GecCC.py
ebcc/codegen/RCC2.py
ebcc/codegen/RCC3.py
ebcc/codegen/RCCD.py
ebcc/codegen/RCCSD.py
ebcc/codegen/RCCSDT.py
ebcc/codegen/RCCSD_SD_1_1.py
ebcc/codegen/RCCSD_SD_1_2.py
ebcc/codegen/RCCSD_S_1_1.py
ebcc/codegen/RCCSDwtwp.py
ebcc/codegen/RCCSDxTx.py
ebcc/codegen/RDCD.py
ebcc/codegen/RDCSD.py
ebcc/codegen/RDFCC2.py
ebcc/codegen/RDFCCD.py
ebcc/codegen/RDFCCSD.py
ebcc/codegen/RDFDCD.py
ebcc/codegen/RDFDCSD.py
ebcc/codegen/RDFQCISD.py
ebcc/codegen/RMP2.py
ebcc/codegen/RMP3.py
ebcc/codegen/RQCISD.py
ebcc/codegen/RecCC.py
ebcc/codegen/UCC2.py
ebcc/codegen/UCC3.py
ebcc/codegen/UCCD.py
ebcc/codegen/UCCSD.py
ebcc/codegen/UCCSDT.py
ebcc/codegen/UCCSD_SD_1_1.py
ebcc/codegen/UCCSD_SD_1_2.py
ebcc/codegen/UCCSD_S_1_1.py
ebcc/codegen/UCCSDwtwp.py
ebcc/codegen/UCCSDxTx.py
ebcc/codegen/UDCD.py
ebcc/codegen/UDCSD.py
ebcc/codegen/UDFCC2.py
ebcc/codegen/UDFCCD.py
ebcc/codegen/UDFCCSD.py
ebcc/codegen/UDFDCD.py
ebcc/codegen/UDFDCSD.py
ebcc/codegen/UDFQCISD.py
ebcc/codegen/UMP2.py
ebcc/codegen/UMP3.py
ebcc/codegen/UQCISD.py
ebcc/codegen/UecCC.py
ebcc/codegen/__init__.py
ebcc/core/__init__.py
ebcc/core/ansatz.py
ebcc/core/damping.py
ebcc/core/davidson.py
ebcc/core/dump.py
ebcc/core/logging.py
ebcc/core/precision.py
ebcc/eom/__init__.py
ebcc/eom/base.py
ebcc/eom/geom.py
ebcc/eom/reom.py
ebcc/eom/ueom.py
ebcc/ext/__init__.py
ebcc/ext/eccc.py
ebcc/ext/fci.py
ebcc/ext/tcc.py
ebcc/ham/__init__.py
ebcc-1.6.1.dist-info/LICENSE.md
ebcc-1.6.1.dist-info/METADATA
ebcc-1.6.1.dist-info/WHEEL
ebcc-1.6.1.dist-info/top_level.txt
ebcc-1.6.1.dist-info/RECORD
