Metadata-Version: 2.1
Name: ebcc
Version: 1.6.1
Summary: Coupled cluster calculations on electron-boson systems
Keywords: quantum,chemistry,electronic,structure,coupled,cluster,electron,boson,ccsd
Classifier: Development Status :: 2 - Pre-Alpha
Classifier: Intended Audience :: Science/Research
Classifier: Intended Audience :: Developers
Classifier: Topic :: Scientific/Engineering
Classifier: Topic :: Software Development
Classifier: Programming Language :: Python
Classifier: Programming Language :: Python :: 3.9
Classifier: Programming Language :: Python :: 3.10
Classifier: Programming Language :: Python :: 3.11
Classifier: Programming Language :: Python :: 3.12
Classifier: Operating System :: MacOS :: MacOS X
Classifier: Operating System :: POSIX :: Linux
Requires-Python: >=3.9
License-File: LICENSE.md
Requires-Dist: numpy>=1.19.0
Requires-Dist: scipy>=1.11.0
Requires-Dist: pyscf>=2.0.0
Requires-Dist: h5py>=3.0.0
Provides-Extra: numpy
Provides-Extra: tensorflow
Requires-Dist: tensorflow>=2.0.0; extra == "tensorflow"
Requires-Dist: opt_einsum>=3.3.0; extra == "tensorflow"
Provides-Extra: jax
Requires-Dist: jax>=0.2.0; extra == "jax"
Requires-Dist: opt_einsum>=3.3.0; extra == "jax"
Requires-Dist: pyscfad>=0.1.8; extra == "jax"
Provides-Extra: cupy
Requires-Dist: cupy>=9.0.0; extra == "cupy"
Requires-Dist: opt_einsum>=3.3.0; extra == "cupy"
Provides-Extra: dev
Requires-Dist: black>=22.6.0; extra == "dev"
Requires-Dist: isort>=5.10.1; extra == "dev"
Requires-Dist: flake8>=3.8.4; extra == "dev"
Requires-Dist: flake8-pyproject>=1.2.3; extra == "dev"
Requires-Dist: flake8-bugbear>=23.0.0; extra == "dev"
Requires-Dist: flake8-docstrings>=1.6.0; extra == "dev"
Requires-Dist: mypy>=1.8.0; extra == "dev"
Requires-Dist: mypy_extensions>=0.4.3; extra == "dev"
Requires-Dist: coverage[toml]>=5.5.0; extra == "dev"
Requires-Dist: pytest>=6.2.4; extra == "dev"
Requires-Dist: pytest-cov>=4.0.0; extra == "dev"
Requires-Dist: mkdocs>=1.6.0; extra == "dev"
Requires-Dist: mkdocs-gen-files>=0.5.0; extra == "dev"
Requires-Dist: mkdocs-section-index>=0.3.0; extra == "dev"
Requires-Dist: mkdocs-autorefs>=1.0.0; extra == "dev"
Requires-Dist: mkdocs-include-markdown-plugin>=6.2.0; extra == "dev"
Requires-Dist: mkdocstrings>=0.25.0; extra == "dev"
Requires-Dist: mkdocstrings-python>=1.10.0; extra == "dev"
